{
  "algorithm": "",
  "chat": [],
  "community": [],
  "description": {
    "en": ""
  },
  "explorer": [],
  "fromSymbol": "MOIN",
  "is_crypto": true,
  "is_minable": false,
  "name": "MoinCoin",
  "network": {
    "t_available_supply": 7821186,
    "t_block_reward": 0,
    "t_max_supply": 0,
    "t_total_supply": 7821186
  },
  "proof_type": "PoW/PoS",
  "quote": ["https://blockmodo.com/quotes/MOIN"],
  "social": ["https://twitter.com/@AeonCoin"],
  "source_code": [],
  "toSymbol": "ALL",
  "type": "COINREGISTRY",
  "version": 1,
  "website": "http://coin.org/"
}